qmenta/__init__.py
qmenta/gui/__init__.py
qmenta/gui/app.py
qmenta/gui/client.py
qmenta/gui/models.py
qmenta/gui/qml/Qmenta/BrainBanner.qml
qmenta/gui/qml/Qmenta/ChooseDirDialog.qml
qmenta/gui/qml/Qmenta/ChooseFilesDialog.qml
qmenta/gui/qml/Qmenta/FileMetaDataDialog.qml
qmenta/gui/qml/Qmenta/LoginPage.qml
qmenta/gui/qml/Qmenta/ProjectsPage.qml
qmenta/gui/qml/Qmenta/QmentaHeader.qml
qmenta/gui/qml/Qmenta/SingleUploadDelegate.qml
qmenta/gui/qml/Qmenta/UploadPage.qml
qmenta/gui/qml/Qmenta/app.qml
qmenta/gui/qml/Qmenta/images/brain_small.svg
qmenta/gui/qml/Qmenta/images/qmenta-logo-small-crop.png
qmenta/gui/qml/Qmenta/qmldir
qmenta/gui/view.py
qmenta_gui-2.6.dist-info/WHEEL
qmenta_gui-2.6.dist-info/METADATA
qmenta_gui-2.6.dist-info/RECORD
