Metadata-Version: 2.1
Name: qmenta-gui
Version: 2.6
Summary: This is a Qt GUI for the QMENTA Core lib to interact with the QMENTA platform.
Home-page: https://www.qmenta.com/
Author: QMENTA
Author-email: dev@qmenta.com
Requires-Python: >=3.6,<3.10
Classifier: Development Status :: 4 - Beta
Classifier: Intended Audience :: Science/Research
Classifier: Programming Language :: Python :: 3
Classifier: Programming Language :: Python :: 3.6
Classifier: Programming Language :: Python :: 3.7
Classifier: Programming Language :: Python :: 3.8
Classifier: Programming Language :: Python :: 3.9
Requires-Dist: PySide2 (>=5.15.2,<6.0.0)
Requires-Dist: importlib-metadata (>=3.3.0,<4.0.0)
Requires-Dist: qmenta-core (>=1.2,<1.3)
